opyra/__init__.py
opyra/adapters/__init__.py
opyra/adapters/base.py
opyra/adapters/mongo.py
opyra/adapters/sql.py
opyra/core.py
opyra/exceptions.py
opyra/hydrator.py
opyra/interpolator.py
opyra/models.py
opyra/query.py
opyra/utils.py
opyra-0.0.5.dist-info/METADATA
opyra-0.0.5.dist-info/WHEEL
opyra-0.0.5.dist-info/licenses/LICENSE
opyra-0.0.5.dist-info/RECORD
