Metadata-Version: 2.4
Name: opyra
Version: 0.0.5
Summary: Unified database operations
License: MIT
License-File: LICENSE
Author: Raymond Ortserga
Author-email: ortserga@gmail.com
Requires-Python: >=3.9,<4.0
Classifier: License :: OSI Approved :: MIT License
Classifier: Programming Language :: Python :: 3
Classifier: Programming Language :: Python :: 3.9
Classifier: Programming Language :: Python :: 3.10
Classifier: Programming Language :: Python :: 3.11
Classifier: Programming Language :: Python :: 3.12
Classifier: Programming Language :: Python :: 3.13
Classifier: Programming Language :: Python :: 3.14
Requires-Dist: inflection (>=0.5.1,<0.6.0)
Requires-Dist: msgspec (>=0.20.0,<0.21.0)
